order_management.py
user_management.py
online_store52-0.1.0.dist-info/METADATA
online_store52-0.1.0.dist-info/WHEEL
online_store52-0.1.0.dist-info/top_level.txt
online_store52-0.1.0.dist-info/RECORD
